pyfreeipa/__init__.py
pyfreeipa/__main__.py
pyfreeipa/Api/__init__.py
pyfreeipa/Api/_utils.py
pyfreeipa/Api/_group/__init__.py
pyfreeipa/Api/_otptoken/__init__.py
pyfreeipa/Api/_user/__init__.py
pyfreeipa/configuration/__init__.py
pyfreeipa-0.2.5.dist-info/licenses/LICENSE
pyfreeipa-0.2.5.dist-info/METADATA
pyfreeipa-0.2.5.dist-info/WHEEL
pyfreeipa-0.2.5.dist-info/top_level.txt
pyfreeipa-0.2.5.dist-info/RECORD
