Metadata-Version: 2.4
Name: pyfreeipa
Version: 0.2.5
Summary: Python FreeIPA API interface
Author: Aaron Hicks
Author-email: aethylred@gmail.com
Maintainer-email: Aaron Hicks <aethylred@gmail.com>
Classifier: Programming Language :: Python :: 3
Classifier: License :: OSI Approved :: Apache Software License
Classifier: Operating System :: OS Independent
License-File: LICENSE
Requires-Dist: certifi
Requires-Dist: chardet
Requires-Dist: idna
Requires-Dist: PyYAML
Requires-Dist: requests
Requires-Dist: typing
Requires-Dist: urllib3
Dynamic: author
Dynamic: author-email
Dynamic: license-file
